{ "_id" : { "$oid" : "568c0a64f7598612373ec4de" }, "salt" : "YK+PqebE99fhs8T+58V2sA==", "displayName" : "Professor Tester", "provider" : "local", "username" : "testpro", "created" : { "$date" : "2016-01-05T13:24:36.810-0500" }, "roles" : [ "professor" ], "profileImageURL" : "modules/users/client/img/profile/default.png", "password" : "+zlgxHgfGfbhacsumXpSQ0vgAkCCYp1bn0wlHPQGpjO+7GXR3aR5IAuT7jLcYeRduDfeFx0fbsKeZ6QFy5gu3A==", "email" : "test@ufl.edu", "lastName" : "Test", "firstName" : "Professor", "__v" : 0, "updated" : { "$date" : "2016-01-05T15:27:04.757-0500" } }
